[
    {
        "id": "1",
        "name": "Unregistered"
    },
    {
        "id": "2",
        "name": "Registered"
    },
    {
        "id": "3",
        "name": "Verified"
    },
    {
        "id": "4",
        "name": "UX.Registered"
    },
    {
        "id": "5",
        "name": "UX.LolosBerkas"
    },
    {
        "id": "6",
        "name": "UX.RevisiBerkas"
    },
    {
        "id": "7",
        "name": "UX.GagalBerkas"
    },
    {
        "id": "8",
        "name": "UX.LolosSeleksi"
    },
    {
        "id": "9",
        "name": "UX.RevisiSeleksi"
    },
    {
        "id": "10",
        "name": "UX.GagalSeleksi"
    },
    {
        "id": "11",
        "name": "DS.Registered"
    },
    {
        "id": "12",
        "name": "DS.LolosBerkas"
    },
    {
        "id": "13",
        "name": "DS.RevisiBerkas"
    },
    {
        "id": "14",
        "name": "DS.GagalBerkas"
    },
    {
        "id": "15",
        "name": "DS.LolosSeleksi"
    },
    {
        "id": "16",
        "name": "DS.RevisiSeleksi"
    },
    {
        "id": "17",
        "name": "DS.GagalSeleksi"
    },
    {
        "id": "18",
        "name": "ISClass.Registered"
    },
    {
        "id": "19",
        "name": "ISClass.Verified"
    },
    {
        "id": "20",
        "name": "ISClass.Rejected"
    },
    {
        "id": "21",
        "name": "BionixRd.Registered"
    },
    {
        "id": "22",
        "name": "BionixRd.VerifiedDp"
    },
    {
        "id": "23",
        "name": "BionixRd.RejectedDp"
    },
    {
        "id": "24",
        "name": "BionixRd.RegisteredPelunasan"
    },
    {
        "id": "25",
        "name": "BionixRd.VerifiedPelunasan"
    },
    {
        "id": "26",
        "name": "BionixRd.RejectedPelunasan"
    },
    {
        "id": "27",
        "name": "BionixRd.RegisteredBerkas"
    },
    {
        "id": "28",
        "name": "BionixRd.VerifiedBerkas"
    },
    {
        "id": "29",
        "name": "BionixRd.RejectedBerkas"
    },
    {
        "id": "30",
        "name": "Bionix.Registered"
    },
    {
        "id": "31",
        "name": "Bionix.VerifiedBerkas"
    },
    {
        "id": "32",
        "name": "Bionix.RejectedBerkas"
    },
    {
        "id": "33",
        "name": "Rise.Registered"
    },
    {
        "id": "34",
        "name": "Rise.Verified"
    },
    {
        "id": "35",
        "name": "Rise.Rejected"
    },
    {
        "id": "36",
        "name": "Rise.Registered.Penyisihan"
    },
    {
        "id": "37",
        "name": "Rise.Verified.Penyisihan"
    },
    {
        "id": "38",
        "name": "Rise.Rejected.Penyisihan"
    },
    {
        "id": "39",
        "name": "Rise.Registered.Pembayaran"
    },
    {
        "id": "40",
        "name": "Rise.Verified.Pembayaran"
    },
    {
        "id": "41",
        "name": "Rise.Rejected.Pembayaran"
    },
    {
        "id": "42",
        "name": "Rise.Registered.Semifinal"
    },
    {
        "id": "43",
        "name": "Rise.Verified.Semifinal"
    },
    {
        "id": "44",
        "name": "Rise.Rejected.Semifinal"
    },
    {
        "id": "45",
        "name": "Rise.Registered.Final"
    },
    {
        "id": "46",
        "name": "Rise.Verified.Final"
    },
    {
        "id": "47",
        "name": "Rise.Rejected.Final"
    },
    {
        "id": "48",
        "name": "BionixRd.Registered.Penyisihan"
    },
    {
        "id": "49",
        "name": "BionixRd.Verified.Penyisihan"
    },
    {
        "id": "50",
        "name": "BionixRd.Rejected.Penyisihan"
    },
    {
        "id": "51",
        "name": "BionixRd.Registered.Semifinal"
    },
    {
        "id": "52",
        "name": "BionixRd.Verified.Semifinal"
    },
    {
        "id": "53",
        "name": "BionixRd.Rejected.Semifinal"
    },
    {
        "id": "54",
        "name": "BionixRd.Registered.Final"
    },
    {
        "id": "55",
        "name": "BionixRd.Verified.Final"
    },
    {
        "id": "56",
        "name": "BionixRd.Rejected.Final"
    }



]
